leet/__init__.py
leet/test_suite/__init__.py
leet/test_suite/comparators.py
leet_suite-0.1.0.dist-info/METADATA
leet_suite-0.1.0.dist-info/WHEEL
leet_suite-0.1.0.dist-info/top_level.txt
leet_suite-0.1.0.dist-info/RECORD
