Metadata-Version: 2.4
Name: leet-suite
Version: 0.1.0
Summary: LeetSuite
Requires-Python: >=3.11
Requires-Dist: ascii-graph>=1.5.2
Requires-Dist: commitizen>=4.9.1
